{
  "page_type": "function",
  "name": "CANstressIsIdle",
  "category": "CANstress",
  "title": "CANstressIsIdle",
  "source": "chm_extract/CANoeCANalyzer/Topics/CAPLfunctions/CANstress/Functions/CAPLfunctionCANstressIsIdle.htm",
  "syntax": [
    "long CANstressIsIdle();"
  ],
  "description": [
    "Serves to query whether the CANstress hardware is in the state Idle."
  ],
  "parameters": [],
  "return": "1: If the CANstress hardware is in the state Idle.",
  "example": {
    "description": [],
    "code": ""
  },
  "availability": [
    [
      "Since Version"
    ]
  ],
  "selectors": [],
  "note": [],
  "complexity": ""
}
