{
  "page_type": "function",
  "name": "FDXDisableFreeRunningMode",
  "category": "Other",
  "title": "FDXDisableFreeRunningMode",
  "source": "chm_extract/CANoeCANalyzer/Topics/CAPLfunctions/Other/Functions/CAPLfunctionFDXDisableFreeRunningMode.htm",
  "syntax": [
    "long FDXDisableFreeRunningMode(long fdxClientHandle, word groupID);"
  ],
  "description": [
    "This function disables the Free Running mode for the specified FDX client. The behavior of the function corresponds to the reception of a FreeRunningCancel command via the CANoe FDX protocol.",
    "You can find further information about the Free Running mode in the manual CANoe_FDX_Protocol_EN.pdf."
  ],
  "parameters": [
    {
      "name": "fdxClientHandle",
      "type": "",
      "description": "FDX Client for which the FreeRunningMode should be activated."
    }
  ],
  "return": "0: Successful function call",
  "example": {
    "description": [],
    "code": ""
  },
  "availability": [
    [
      "Since Version"
    ]
  ],
  "selectors": [],
  "note": [],
  "complexity": ""
}
