{
  "page_type": "function",
  "name": "fileRewind",
  "category": "Other",
  "title": "fileRewind",
  "source": "chm_extract/CANoeCANalyzer/Topics/CAPLfunctions/Other/Functions/CAPLfunctionFileRewind.htm",
  "syntax": [
    "long fileRewind (dword fileHandle);"
  ],
  "description": [
    "This function resets the position pointer to the beginning of the file."
  ],
  "parameters": [],
  "return": "If an error occurs, the return value is 0, else 1.",
  "example": {
    "description": [],
    "code": ""
  },
  "availability": [
    [
      "Since Version"
    ]
  ],
  "selectors": [],
  "note": [],
  "complexity": ""
}
