{
  "page_type": "function",
  "name": "sqrt",
  "category": "Other",
  "title": "sqrt",
  "source": "chm_extract/CANoeCANalyzer/Topics/CAPLfunctions/Other/Functions/CAPLfunctionSqrt.htm",
  "syntax": [
    "double sqrt(double x);"
  ],
  "description": [
    "Calculates the square root."
  ],
  "parameters": [],
  "return": "Square root of x.",
  "example": {
    "description": [],
    "code": "double x;\nx = sqrt(4.0); // Result 2.0"
  },
  "availability": [
    [
      "Since Version"
    ]
  ],
  "selectors": [],
  "note": [],
  "complexity": ""
}
