{
  "page_type": "function",
  "name": "timeNowNS, timeNowInt64",
  "category": "Other",
  "title": "timeNowNS, timeNowInt64",
  "source": "chm_extract/CANoeCANalyzer/Topics/CAPLfunctions/Other/Functions/CAPLfunctionTimeNowNS.htm",
  "syntax": [
    "float TimeNowNS();"
  ],
  "description": [
    "Supplies the current simulation time.",
    "The simulation time can be correlated with the hardware results of the interface cards (e.g. CANcardXL).The resolution of this time is dependent upon the hardware used (usually a millisecond or better).",
    "Depending on the hardware configuration, the simulation time",
    "or"
  ],
  "parameters": [],
  "return": "Simulation time in nanoseconds.",
  "example": {
    "description": [],
    "code": ""
  },
  "availability": [
    [
      "Since Version"
    ]
  ],
  "selectors": [],
  "note": [],
  "complexity": ""
}
