{
  "page_type": "function",
  "name": "J1939TestChkControl_Destroy",
  "category": "J1939",
  "title": "J1939TestChkControl_Destroy",
  "source": "chm_extract_v15/CANoeCANalyzer/Topics/CAPLFunctions/J1939/J1939TestServiceLibrary/Functions/CAPLfunctionJ1939TestChkControlDestroy.htm",
  "syntax": [
    "long J1939TestChkControl_Destroy_Destroy( long checkId );"
  ],
  "description": [
    "The check is destroyed and cannot be accessed anymore. Its resources are freed and may be reused."
  ],
  "parameters": [
    {
      "name": "checkId",
      "type": "",
      "description": "identifier of the check to destroy"
    }
  ],
  "return": "",
  "example": {
    "description": [],
    "code": "long cycleCheck;\ncycleCheck = J1939TestChkCreate_AbsCycleTimeViolation( 1, 2, 0xf123, 0.8, 1.2, \"CycleCallback\" );\n\nJ1939TestChkControl_Start( cycleCheck );\n//...\nJ1939TestChkControl_Destroy_Destroy( cycleCheck );"
  },
  "availability": [
    [
      "CANalyzer",
      "CANoe",
      "CANoe4SW Server Edition (Windows)",
      "CANoe4SW Server Edition (Linux)",
      "CANoe4SW",
      "vTESTstudio"
    ],
    [
      "Since Version",
      "—",
      "7.1",
      "13.0",
      "—",
      "—",
      "1.1 SP2"
    ],
    [
      "Restricted To",
      "—",
      "J1939",
      "J1939",
      "—",
      "—",
      "J1939"
    ],
    [
      "CANalyzer Measurement Setup (Transmit Branch)",
      "—",
      "N/A",
      "N/A",
      "N/A",
      "N/A",
      "N/A"
    ],
    [
      "CANoe Measurement Setup / CANalyzer Analysis Branch",
      "—",
      "—",
      "—",
      "—",
      "N/A",
      "N/A"
    ],
    [
      "CANoe Simulation Setup",
      "N/A",
      "—",
      "—",
      "—",
      "N/A",
      "N/A"
    ],
    [
      "CANoe System and Communication Setup",
      "N/A",
      "—",
      "—",
      "—",
      "—",
      "N/A"
    ],
    [
      "CANoe Test Setup for Test Modules",
      "N/A",
      "✔",
      "✔",
      "—",
      "N/A",
      "N/A"
    ],
    [
      "CANoe Test Setup for Test Units",
      "N/A",
      "✔",
      "✔",
      "—",
      "—",
      "N/A"
    ],
    [
      "32-Bit",
      "—",
      "✔",
      "✔",
      "N/A",
      "—",
      "N/A"
    ],
    [
      "64-Bit",
      "—",
      "✔",
      "✔",
      "—",
      "—",
      "N/A"
    ]
  ],
  "selectors": [],
  "note": [],
  "complexity": ""
}
