{
  "page_type": "function",
  "name": "MCDInit",
  "category": "Obsolete",
  "title": "MCDInit",
  "source": "chm_extract/CANoeCANalyzer/Topics/CAPLfunctions/Obsolete/Functions/CAPLfunctionMCDInit.htm",
  "syntax": [
    "long MCDInit ()"
  ],
  "description": [
    "Initialisation of the MCD server. CANape will be started in non modal mode.",
    "This function must only be called during the initialisation phase of the measurement (MeasurementInit)."
  ],
  "parameters": [],
  "return": "0: OK",
  "example": {
    "description": [],
    "code": ""
  },
  "availability": [
    [
      "Up to Version"
    ]
  ],
  "selectors": [],
  "note": [],
  "complexity": ""
}
