{
  "page_type": "function",
  "name": "mostGetShutdownFlag",
  "category": "MOST",
  "title": "mostGetShutdownFlag",
  "source": "chm_extract/CANoeCANalyzer/Topics/CAPLfunctions/MOST/Functions/CAPLfunctionMOSTGetShutdownFlag.htm",
  "syntax": [
    "long mostGetShutdownFlag(long channel)"
  ],
  "description": [],
  "parameters": [
    {
      "name": "channel",
      "type": "",
      "description": "Application channel number."
    }
  ],
  "return": "1: Shutdown Flag set.",
  "example": {
    "description": [],
    "code": ""
  },
  "availability": [
    [
      "Since Version"
    ]
  ],
  "selectors": [],
  "note": [],
  "complexity": ""
}
