{
  "page_type": "function",
  "name": "ARILControlStop",
  "category": "AUTOSARpduIL",
  "title": "ARILControlStop",
  "source": "chm_extract/CANoeCANalyzer/Topics/CAPLfunctions/AUTOSARpduIL/Functions/CAPLfunctionARILControlStop.htm",
  "syntax": [
    "long ARILControlStop()"
  ],
  "description": [
    "Stops sending of PDUs."
  ],
  "parameters": [],
  "return": "0: No error.",
  "example": {
    "description": [],
    "code": ""
  },
  "availability": [
    [
      "Since Version"
    ]
  ],
  "selectors": [],
  "note": [],
  "complexity": ""
}
