{
  "page_type": "notes",
  "name": "Classes in CAPL",
  "category": "ObjectOrientedProg",
  "title": "Classes in CAPL",
  "source": "chm_extract_v15/CANoeCANalyzer/Topics/CAPLFunctions/ObjectOrientedProg/CAPLfunctionsOOPClassesObjects.htm",
  "syntax": [],
  "description": [
    "In CAPL predefined data types are available that can be used like classes in object-oriented programming languages such as C++.",
    "Detailed Description about Classes and Objects in CAPL"
  ],
  "parameters": [],
  "return": "",
  "example": {
    "description": [],
    "code": ""
  },
  "availability": [],
  "selectors": [],
  "note": [],
  "complexity": "",
  "tables": [
    [
      [
        "Version 15© Vector Informatik GmbH"
      ]
    ]
  ]
}
