{
  "page_type": "concept",
  "name": "Option Mapping",
  "category": "DBC",
  "subcategory": "windows",
  "title": "Option Mapping",
  "source": "chm_extract_v15/CANeds/Topics/windows/options/Option_Mapping.htm",
  "intro": [],
  "intro_tables": [],
  "intro_code_blocks": [],
  "sections": [
    {
      "heading": "PDO Mapping Entries",
      "level": 2,
      "content": {
        "paragraphs": [
          "If this check box is selected then the mapping entries in PDOs are adjusted if an index or sub index of a mapped object is changed."
        ],
        "tables": [
          [
            [
              "Version 15© Vector Informatik GmbH"
            ]
          ]
        ],
        "code_blocks": []
      }
    }
  ]
}
