{
  "page_type": "function",
  "name": "lookupDistObjReference",
  "category": "DistributedObjects",
  "title": "lookupDistObjReference",
  "source": "chm_extract_v15/CANoeCANalyzer/Topics/CAPLFunctions/DistributedObjects/Functions/CAPLfunctionLookupDistObjReference.htm",
  "syntax": [
    "distObjReferenceRef * lookupDistObjReference(char path[]);"
  ],
  "description": [
    "Obtains a reference by using a string.",
    "A downcast can be used to get a more concrete type."
  ],
  "parameters": [
    {
      "name": "path",
      "type": "",
      "description": "Fully qualified name of the reference."
    }
  ],
  "return": "Reference with the given path.\nInvalid reference if nothing was found.",
  "example": {
    "description": [],
    "code": "// vCDL\nversion 1.3;\nnamespace SomeNamespace {\n  interface SomeInterface {\n    internal data int32 d;\n  }\n  reference<SomeInterface> Ref;\n}\n\n// CAPL\non key 'a' {\n  distObjReferenceRef SomeInterface x;\n\n  // downcast with typename\n  x = (distObjReferenceRef SomeInterface)lookupDistObjReference(\"SomeNamespace::Ref\");\n\n  // downcast with __type_of\n  x = (__type_of(x))lookupDistObjReference(\"SomeNamespace::Ref\");\n}"
  },
  "availability": [
    [
      "CANalyzer",
      "CANoe",
      "CANoe4SW Server Edition (Windows)",
      "CANoe4SW Server Edition (Linux)",
      "CANoe4SW",
      "vTESTstudio"
    ],
    [
      "Since Version",
      "—",
      "14",
      "14",
      "15",
      "14",
      "5.0 SP3"
    ],
    [
      "Restricted To",
      "—",
      "—",
      "—",
      "—",
      "—",
      "—"
    ],
    [
      "CANalyzer Measurement Setup (Transmit Branch)",
      "—",
      "N/A",
      "N/A",
      "N/A",
      "N/A",
      "N/A"
    ],
    [
      "CANoe Measurement Setup / CANalyzer Analysis Branch",
      "—",
      "✔",
      "✔",
      "✔",
      "N/A",
      "N/A"
    ],
    [
      "CANoe Simulation Setup",
      "N/A",
      "✔",
      "✔",
      "✔",
      "N/A",
      "N/A"
    ],
    [
      "CANoe System and Communication Setup",
      "N/A",
      "✔",
      "✔",
      "✔",
      "✔",
      "N/A"
    ],
    [
      "CANoe Test Setup for Test Modules",
      "N/A",
      "✔",
      "✔",
      "✔",
      "N/A",
      "N/A"
    ],
    [
      "CANoe Test Setup for Test Units",
      "N/A",
      "✔",
      "✔",
      "✔",
      "✔",
      "N/A"
    ],
    [
      "32-Bit",
      "—",
      "✔",
      "✔",
      "N/A",
      "✔",
      "N/A"
    ],
    [
      "64-Bit",
      "—",
      "✔",
      "✔",
      "✔",
      "✔",
      "N/A"
    ]
  ],
  "selectors": [],
  "note": [],
  "complexity": ""
}
